Metadata-Version: 2.1
Name: alphabases
Version: 0.10.2
Summary: SDK of alpha@gdc group.
Author: Ricardo
Author-email: gzsushixuan@corp.netease.com
License: UNKNOWN
Platform: UNKNOWN
License-File: LICENSE.txt
